execnet/__init__.py
execnet/_version.py
execnet/gateway.py
execnet/gateway_base.py
execnet/gateway_bootstrap.py
execnet/gateway_io.py
execnet/gateway_socket.py
execnet/multi.py
execnet/py.typed
execnet/rsync.py
execnet/rsync_remote.py
execnet/xspec.py
execnet/script/__init__.py
execnet/script/loop_socketserver.py
execnet/script/quitserver.py
execnet/script/shell.py
execnet/script/socketserver.py
execnet/script/socketserverservice.py
execnet-2.1.0.dist-info/METADATA
execnet-2.1.0.dist-info/WHEEL
execnet-2.1.0.dist-info/licenses/LICENSE
execnet-2.1.0.dist-info/RECORD
